s3site.py
setup.py
s3site.egg-info/PKG-INFO
s3site.egg-info/SOURCES.txt
s3site.egg-info/dependency_links.txt
s3site.egg-info/entry_points.txt
s3site.egg-info/requires.txt
s3site.egg-info/top_level.txt