Metadata-Version: 1.1
Name: s3site
Version: 0.2
Summary: A command line tool to manage static sites on Amazons S3 service
Home-page: https://github.com/bensentropy/s3site
Author: Ben Olsen
Author-email: me@bensentorpy.com
License: UNKNOWN
Download-URL: https://github.com/bensentropy/s3site/archive/master.zip
Platform: UNKNOWN
